session_mgmt_mcp/__init__.py
session_mgmt_mcp/__main__.py
session_mgmt_mcp/acb_cache_adapter.py
session_mgmt_mcp/advanced_features.py
session_mgmt_mcp/advanced_search.py
session_mgmt_mcp/app_monitor.py
session_mgmt_mcp/cli.py
session_mgmt_mcp/context_manager.py
session_mgmt_mcp/crackerjack_integration.py
session_mgmt_mcp/health_checks.py
session_mgmt_mcp/interruption_manager.py
session_mgmt_mcp/knowledge_graph_db.py
session_mgmt_mcp/llm_providers.py
session_mgmt_mcp/memory_optimizer.py
session_mgmt_mcp/multi_project_coordinator.py
session_mgmt_mcp/natural_scheduler.py
session_mgmt_mcp/parameter_models.py
session_mgmt_mcp/quality_engine.py
session_mgmt_mcp/reflection_tools.py
session_mgmt_mcp/resource_cleanup.py
session_mgmt_mcp/search_enhanced.py
session_mgmt_mcp/server.py
session_mgmt_mcp/server_core.py
session_mgmt_mcp/server_optimized.py
session_mgmt_mcp/serverless_mode.py
session_mgmt_mcp/session_commands.py
session_mgmt_mcp/settings.py
session_mgmt_mcp/shutdown_manager.py
session_mgmt_mcp/team_knowledge.py
session_mgmt_mcp/token_optimizer.py
session_mgmt_mcp/trailing_period_removal_summary.md
session_mgmt_mcp/types.py
session_mgmt_mcp/worktree_manager.py
session_mgmt_mcp/adapters/__init__.py
session_mgmt_mcp/adapters/knowledge_graph_adapter.py
session_mgmt_mcp/adapters/knowledge_graph_adapter_acb_investigation.py
session_mgmt_mcp/adapters/reflection_adapter.py
session_mgmt_mcp/adapters/serverless_storage_adapter.py
session_mgmt_mcp/adapters/session_storage_adapter.py
session_mgmt_mcp/adapters/storage_registry.py
session_mgmt_mcp/backends/__init__.py
session_mgmt_mcp/backends/acb_cache_backend.py
session_mgmt_mcp/backends/base.py
session_mgmt_mcp/backends/local_backend.py
session_mgmt_mcp/backends/redis_backend.py
session_mgmt_mcp/backends/s3_backend.py
session_mgmt_mcp/core/__init__.py
session_mgmt_mcp/core/features.py
session_mgmt_mcp/core/permissions.py
session_mgmt_mcp/core/session_manager.py
session_mgmt_mcp/core/lifecycle/__init__.py
session_mgmt_mcp-0.9.3.dist-info/METADATA
session_mgmt_mcp-0.9.3.dist-info/WHEEL
session_mgmt_mcp-0.9.3.dist-info/entry_points.txt
session_mgmt_mcp-0.9.3.dist-info/licenses/LICENSE
session_mgmt_mcp-0.9.3.dist-info/RECORD
