Metadata-Version: 2.4
Name: session-mgmt-mcp
Version: 0.9.3
Summary: MCP server for Claude session management and conversation memory
Project-URL: Homepage, https://github.com/lesleslie/session-mgmt-mcp
Project-URL: Issues, https://github.com/lesleslie/session-mgmt-mcp/issues
Project-URL: Repository, https://github.com/lesleslie/session-mgmt-mcp
Author-email: Les Leslie <les@wedgwoodwebworks.com>
License: BSD 3-Clause License
License-File: LICENSE
Keywords: ai-tools,anthropic,claude,conversation-memory,mcp,reflection,session-management
Classifier: Development Status :: 4 - Beta
Classifier: Intended Audience :: Developers
Classifier: License :: OSI Approved :: BSD License
Classifier: Programming Language :: Python :: 3 :: Only
Classifier: Programming Language :: Python :: 3.13
Classifier: Topic :: Software Development :: Libraries :: Python Modules
Classifier: Topic :: System :: System Shells
Classifier: Topic :: Utilities
Requires-Python: >=3.13
Requires-Dist: acb>=0.31.6
Requires-Dist: aiocache>=0.12.3
Requires-Dist: bevy>=3.1.0b12
Requires-Dist: crackerjack>=0.44.28
Requires-Dist: duckdb>=1.4.2
Requires-Dist: fastapi>=0.121.2
Requires-Dist: fastmcp>=2.13.1
Requires-Dist: httpx<1.0.0,>=0.28.1
Requires-Dist: jinja2-async-environment>=0.18.5
Requires-Dist: jinja2>=3.1.6
Requires-Dist: mcp-common>=0.3.2
Requires-Dist: numpy>=2.3.5
Requires-Dist: onnxruntime<1.24.0.dev,>=1.23.2
Requires-Dist: psutil>=7.1.3
Requires-Dist: pydantic-settings>=2.12.0
Requires-Dist: pydantic>=2.12.4
Requires-Dist: rich>=14.2.0
Requires-Dist: structlog>=25.5.0
Requires-Dist: tiktoken>=0.12.0
Requires-Dist: tomli>=2.3.0
Requires-Dist: transformers>=4.57.1
Requires-Dist: typer>=0.20.0
